{
    "watch":[
        {
            "image":"https://images.unsplash.com/photo-1620625515032-6ed0c1790c75?ixlib=rb-4.0.3&ixid=M3wxMjA3fDB8MHxzZWFyY2h8Mnx8cm9sZXh8ZW58MHx8MHx8fDA%3D&auto=format&fit=crop&w=500&q=60",
            "price":4000,
            "category":"watch",
            "name":"Rolex"
        },
        {
            "image":"https://images.unsplash.com/photo-1684573573596-38d19a0c0776?ixlib=rb-4.0.3&ixid=M3wxMjA3fDB8MHxzZWFyY2h8OHx8dGl0YW4lMjB3YXRjaHxlbnwwfHwwfHx8MA%3D%3D&auto=format&fit=crop&w=500&q=60",
            "price":1000,
            "category":"watch",
            "name":"Titan"
        },
        {
            "image":"https://images.unsplash.com/photo-1522312346375-d1a52e2b99b3?ixlib=rb-4.0.3&ixid=M3wxMjA3fDB8MHxzZWFyY2h8M3x8d2F0Y2h8ZW58MHx8MHx8fDA%3D&auto=format&fit=crop&w=500&q=60",
            "price":2000,
            "category":"watch",
            "name":"Rolex"
        },
        {
            "image":"https://images.unsplash.com/photo-1684573161050-d860d90a8a20?ixlib=rb-4.0.3&ixid=M3wxMjA3fDB8MHxzZWFyY2h8MTR8fHRpdGFuJTIwd2F0Y2h8ZW58MHx8MHx8fDA%3D&auto=format&fit=crop&w=500&q=60",
            "price":1500,
            "category":"watch",
            "name":"Titan"
        },
        {
            "image":"https://images.unsplash.com/photo-1539874754764-5a96559165b0?ixlib=rb-4.0.3&ixid=M3wxMjA3fDB8MHxzZWFyY2h8MTJ8fHdhdGNofGVufDB8fDB8fHww&auto=format&fit=crop&w=500&q=600",
            "price":500,
            "category":"watch",
            "name":"Fossil"
        } 
        
    ],
    "cloth":[
        {
            "image":"https://images.unsplash.com/photo-1585487000160-6ebcfceb0d03?ixlib=rb-4.0.3&ixid=M3wxMjA3fDB8MHxzZWFyY2h8MTR8fGNsb3RoaW5nfGVufDB8fDB8fHww&auto=format&fit=crop&w=500&q=60",
            "price":1200,
            "category":"cloth",
            "name":"Skirt"
        },
        {
            "image":"https://images.unsplash.com/photo-1552664199-fd31f7431a55?ixlib=rb-4.0.3&ixid=M3wxMjA3fDB8MHxzZWFyY2h8MTJ8fGNsb3RoaW5nfGVufDB8fDB8fHww&auto=format&fit=crop&w=500&q=60",
            "price":1000,
            "category":"cloth",
            "name":"Shirt"
        },
        {
            "image":"https://images.unsplash.com/photo-1576566588028-4147f3842f27?ixlib=rb-4.0.3&ixid=M3wxMjA3fDB8MHxzZWFyY2h8MTd8fGNsb3RoaW5nfGVufDB8fDB8fHww&auto=format&fit=crop&w=500&q=60",
            "price":2000,
            "category":"cloth",
            "name":"T-Shirt"
        },
        {
            "image":"https://images.unsplash.com/photo-1600950207944-0d63e8edbc3f?ixlib=rb-4.0.3&ixid=M3wxMjA3fDB8MHxzZWFyY2h8Mjh8fGNsb3RoaW5nfGVufDB8fDB8fHww&auto=format&fit=crop&w=500&q=60",
            "price":1500,
            "category":"cloth",
            "name":"Hoddie"
        },
        {
            "image":"https://images.unsplash.com/photo-1588359348347-9bc6cbbb689e?ixlib=rb-4.0.3&ixid=M3wxMjA3fDB8MHxzZWFyY2h8MzV8fGNsb3RoaW5nfGVufDB8fDB8fHww&auto=format&fit=crop&w=500&q=60",
            "price":500,
            "category":"cloth",
            "name":"Shirt"
        } 
        
    ]
   
}